odoo/addons/sale_partner_delivery_window/README.rst
odoo/addons/sale_partner_delivery_window/__init__.py
odoo/addons/sale_partner_delivery_window/__manifest__.py
odoo/addons/sale_partner_delivery_window/i18n/sale_partner_delivery_window.pot
odoo/addons/sale_partner_delivery_window/models/__init__.py
odoo/addons/sale_partner_delivery_window/models/res_partner.py
odoo/addons/sale_partner_delivery_window/models/sale_order.py
odoo/addons/sale_partner_delivery_window/models/sale_order_line.py
odoo/addons/sale_partner_delivery_window/models/stock_picking.py
odoo/addons/sale_partner_delivery_window/readme/CONFIGURE.rst
odoo/addons/sale_partner_delivery_window/readme/CONTRIBUTORS.rst
odoo/addons/sale_partner_delivery_window/readme/DESCRIPTION.rst
odoo/addons/sale_partner_delivery_window/readme/USAGE.rst
odoo/addons/sale_partner_delivery_window/static/description/icon.png
odoo/addons/sale_partner_delivery_window/static/description/index.html
odoo/addons/sale_partner_delivery_window/tests/__init__.py
odoo/addons/sale_partner_delivery_window/tests/test_sale_delivery_window.py
odoo13_addon_sale_partner_delivery_window-13.0.1.3.0.dist-info/METADATA
odoo13_addon_sale_partner_delivery_window-13.0.1.3.0.dist-info/WHEEL
odoo13_addon_sale_partner_delivery_window-13.0.1.3.0.dist-info/top_level.txt
odoo13_addon_sale_partner_delivery_window-13.0.1.3.0.dist-info/RECORD
