Metadata-Version: 2.1
Name: odoo13-addon-sale-partner-delivery-window
Version: 13.0.1.3.0
Summary: Schedule delivery orders according to delivery window preferences
Home-page: https://github.com/OCA/sale-workflow
Author: Camptocamp, Odoo Community Association (OCA)
Author-email: support@odoo-community.org
License: AGPL-3
Platform: UNKNOWN
Classifier: Programming Language :: Python
Classifier: Framework :: Odoo
Classifier: License :: OSI Approved :: GNU Affero General Public License v3
Classifier: Development Status :: 3 - Alpha
Requires-Python: >=3.5
Requires-Dist: odoo13-addon-stock-partner-delivery-window
Requires-Dist: odoo (<13.1dev,>=13.0a)
